{
 "id": "wr1OHeNb",
 "name": "demoroomclassic",
 "engine": "2.5.1",
 "setup": {
  "engine": "2.5.0",
  "version": "0.23.0-dev",
  "type": "grid-square",
  "gridSize": 64,
  "gridWidth": 64,
  "gridHeight": 64,
  "colors": [
   {
    "name": "Black",
    "value": "#202020"
   },
   {
    "name": "White",
    "value": "#e8e8e8"
   },
   {
    "name": "Red",
    "value": "#b32d35"
   },
   {
    "name": "Orange",
    "value": "#b05a11"
   },
   {
    "name": "Yellow",
    "value": "#af9700"
   },
   {
    "name": "Green",
    "value": "#317501"
   },
   {
    "name": "Cyan",
    "value": "#40bfbf"
   },
   {
    "name": "Blue",
    "value": "#3387b0"
   },
   {
    "name": "Indigo",
    "value": "#2e4d7b"
   },
   {
    "name": "Violet",
    "value": "#730fb1"
   },
   {
    "name": "Magenta",
    "value": "#bf40bf"
   },
   {
    "name": "Gray A",
    "value": "#606060"
   },
   {
    "name": "Gray B",
    "value": "#a0a0a0"
   }
  ],
  "borders": [
   {
    "name": "Black",
    "value": "#202020"
   },
   {
    "name": "White",
    "value": "#e8e8e8"
   },
   {
    "name": "Red",
    "value": "#b32d35"
   },
   {
    "name": "Orange",
    "value": "#b05a11"
   },
   {
    "name": "Yellow",
    "value": "#af9700"
   },
   {
    "name": "Green",
    "value": "#317501"
   },
   {
    "name": "Cyan",
    "value": "#40bfbf"
   },
   {
    "name": "Blue",
    "value": "#3387b0"
   },
   {
    "name": "Indigo",
    "value": "#2e4d7b"
   },
   {
    "name": "Violet",
    "value": "#730fb1"
   },
   {
    "name": "Magenta",
    "value": "#bf40bf"
   },
   {
    "name": "Gray A",
    "value": "#606060"
   },
   {
    "name": "Gray B",
    "value": "#a0a0a0"
   }
  ]
 },
 "library": {
  "overlay": [
   {
    "id": "aRGFb300",
    "lid": "T28mo300",
    "name": "_.area",
    "type": "overlay",
    "bg": "1",
    "media": [],
    "mask": "_.area.1x1xX.1.svg"
   },
   {
    "id": "Z9lUg100",
    "lid": "ig-Kt200",
    "name": "_.area",
    "type": "overlay",
    "w": 2,
    "bg": "1",
    "media": [],
    "mask": "_.area.2x2xX.1.svg"
   },
   {
    "id": "Qz08B000",
    "lid": "Bu07x200",
    "name": "_.area",
    "type": "overlay",
    "w": 3,
    "bg": "1",
    "media": [],
    "mask": "_.area.3x3xX.1.svg"
   },
   {
    "id": "SKT2Y200",
    "lid": "wPXsm000",
    "name": "_.area",
    "type": "overlay",
    "w": 4,
    "bg": "1",
    "media": [],
    "mask": "_.area.4x4xX.1.svg"
   },
   {
    "id": "v5IOb300",
    "lid": "XVoPF000",
    "name": "_.area",
    "type": "overlay",
    "w": 5,
    "bg": "1",
    "media": [],
    "mask": "_.area.5x5xX.1.svg"
   },
   {
    "id": "jWJP6100",
    "lid": "yk-7s000",
    "name": "_.circle",
    "type": "overlay",
    "bg": "1",
    "media": [],
    "mask": "_.circle.1x1xX.1.svg"
   },
   {
    "id": "k4gCt300",
    "lid": "z68Zp100",
    "name": "_.circle",
    "type": "overlay",
    "w": 2,
    "bg": "1",
    "media": [],
    "mask": "_.circle.2x2xX.1.svg"
   },
   {
    "id": "xJ5mG200",
    "lid": "E8HmA100",
    "name": "_.circle",
    "type": "overlay",
    "w": 3,
    "bg": "1",
    "media": [],
    "mask": "_.circle.3x3xX.1.svg"
   },
   {
    "id": "jyYsL000",
    "lid": "Fygdi300",
    "name": "_.circle",
    "type": "overlay",
    "w": 4,
    "bg": "1",
    "media": [],
    "mask": "_.circle.4x4xX.1.svg"
   },
   {
    "id": "m8DI6100",
    "lid": "CHPAJ300",
    "name": "_.circle",
    "type": "overlay",
    "w": 5,
    "bg": "1",
    "media": [],
    "mask": "_.circle.5x5xX.1.svg"
   },
   {
    "id": "rfCka100",
    "lid": "LZCOB200",
    "name": "_.cubeLarge",
    "type": "overlay",
    "bg": "3",
    "media": [
     "_.cubeLarge.1x1x1.3.png"
    ],
    "mask": "_.cubeLarge.1x1xX.3.png"
   },
   {
    "id": "je0yw100",
    "lid": "dojMw300",
    "name": "_.cubeMedium",
    "type": "overlay",
    "bg": "3",
    "media": [
     "_.cubeMedium.1x1x1.3.png"
    ],
    "mask": "_.cubeMedium.1x1xX.3.png"
   },
   {
    "id": "R_vpv100",
    "lid": "xwTgs300",
    "name": "_.cubeSmall",
    "type": "overlay",
    "bg": "3",
    "media": [
     "_.cubeSmall.1x1x1.3.png"
    ],
    "mask": "_.cubeSmall.1x1xX.3.png"
   },
   {
    "id": "HokYV100",
    "lid": "y2e6H000",
    "name": "_.pin",
    "type": "overlay",
    "w": 2,
    "bg": "3",
    "media": [
     "_.pin.2x2x1.3.png"
    ],
    "mask": "_.pin.2x2xX.3.svg"
   },
   {
    "id": "goUQT300",
    "lid": "zNVkI000",
    "name": "_.wall",
    "type": "overlay",
    "bg": "1",
    "media": [
     "_.wall.1x1x1.1.png"
    ],
    "mask": "_.wall.1x1xX.1.png"
   },
   {
    "id": "mKjdO100",
    "lid": "Lv6KO300",
    "name": "_.zone",
    "type": "overlay",
    "bg": "1",
    "media": [],
    "mask": "_.zone.1x1xX.1.svg"
   },
   {
    "id": "JgIuD300",
    "lid": "udFmR200",
    "name": "_.zone",
    "type": "overlay",
    "w": 2,
    "bg": "1",
    "media": [],
    "mask": "_.zone.2x2xX.1.svg"
   },
   {
    "id": "kVTKu200",
    "lid": "d3eZa200",
    "name": "_.zone",
    "type": "overlay",
    "w": 3,
    "bg": "1",
    "media": [],
    "mask": "_.zone.3x3xX.1.svg"
   },
   {
    "id": "SR0A5000",
    "lid": "MENAY000",
    "name": "_.zone",
    "type": "overlay",
    "w": 4,
    "bg": "1",
    "media": [],
    "mask": "_.zone.4x4xX.1.svg"
   },
   {
    "id": "fslkO100",
    "lid": "fCmd1000",
    "name": "_.zone",
    "type": "overlay",
    "w": 5,
    "bg": "1",
    "media": [],
    "mask": "_.zone.5x5xX.1.svg"
   }
  ],
  "tile": [
   {
    "id": "i_6yU100",
    "lid": "SoKu5200",
    "name": "_.glassDark",
    "type": "tile",
    "w": 2,
    "bg": "transparent",
    "media": [
     "_.glassDark.2x2x1.transparent.png"
    ]
   },
   {
    "id": "rxt72100",
    "lid": "xhnDI000",
    "name": "_.glassLight",
    "type": "tile",
    "w": 2,
    "bg": "transparent",
    "media": [
     "_.glassLight.2x2x1.transparent.png"
    ]
   },
   {
    "id": "ayync200",
    "lid": "gQ6Pe200",
    "name": "backgammon",
    "type": "tile",
    "w": 14,
    "h": 12,
    "bg": "#DDBC95",
    "media": [
     "backgammon.14x12x1.DDBC95.svg"
    ],
    "base": "backgammon.14x12x0.DDBC95.jpg"
   },
   {
    "id": "r67iL000",
    "lid": "Y6aoL100",
    "name": "chess",
    "type": "tile",
    "w": 8,
    "bg": "#b7b9ca",
    "media": [
     "chess.8x8.b7b9ca.jpg"
    ]
   },
   {
    "id": "ZFRq_100",
    "lid": "lWh16200",
    "name": "go.09x09",
    "type": "tile",
    "w": 9,
    "bg": "#DDBC95",
    "media": [
     "go.09x09.9x9x1.DDBC95.svg"
    ],
    "base": "go.09x09.9x9x0.DDBC95.jpg"
   },
   {
    "id": "Ezd_d200",
    "lid": "sHieO100",
    "name": "go.13x13",
    "type": "tile",
    "w": 13,
    "bg": "#DDBC95",
    "media": [
     "go.13x13.13x13x1.DDBC95.svg"
    ],
    "base": "go.13x13.13x13x0.DDBC95.jpg"
   },
   {
    "id": "BTxMM200",
    "lid": "rYebw200",
    "name": "go.19x19",
    "type": "tile",
    "w": 19,
    "bg": "#DDBC95",
    "media": [
     "go.19x19.19x19x1.DDBC95.svg"
    ],
    "base": "go.19x19.19x19x0.DDBC95.jpg"
   },
   {
    "id": "l_yuM200",
    "lid": "MUwjA300",
    "name": "mills",
    "type": "tile",
    "w": 10,
    "bg": "#DDBC95",
    "media": [
     "mills.10x10x1.DDBC95.svg"
    ],
    "base": "mills.10x10x0.DDBC95.jpg"
   },
   {
    "id": "yPMhS300",
    "lid": "z6iPq300",
    "name": "oware",
    "type": "tile",
    "w": 18,
    "h": 6,
    "bg": "#DDBC95",
    "media": [
     "oware.18x6x1.DDBC95.svg"
    ],
    "base": "oware.18x6x0.DDBC95.jpg"
   },
   {
    "id": "zNYey200",
    "lid": "aR3Vu100",
    "name": "pachisi",
    "type": "tile",
    "w": 12,
    "bg": "#DDBC95",
    "media": [
     "pachisi.12x12x1.DDBC95.svg"
    ],
    "base": "pachisi.12x12x0.DDBC95.jpg"
   },
   {
    "id": "xrW3P300",
    "lid": "N3mCH100",
    "name": "solitaire",
    "type": "tile",
    "w": 8,
    "bg": "#DDBC95",
    "media": [
     "solitaire.8x8x1.DDBC95.svg"
    ],
    "base": "solitaire.8x8x0.DDBC95.jpg"
   },
   {
    "id": "uR37n100",
    "lid": "GTJ-P300",
    "name": "ticTacToe",
    "type": "tile",
    "w": 6,
    "bg": "#DDBC95",
    "media": [
     "ticTacToe.6x6x1.DDBC95.svg"
    ],
    "base": "ticTacToe.6x6x0.DDBC95.jpg"
   }
  ],
  "token": [
   {
    "id": "p9Hr0300",
    "lid": "wAksS100",
    "name": "_.bead",
    "type": "token",
    "bg": "1",
    "media": [
     "_.bead.1x1x1.1.png"
    ]
   },
   {
    "id": "G8QAJ200",
    "lid": "mAa-Q300",
    "name": "_.letter",
    "type": "token",
    "bg": "1",
    "media": [
     "_.letter.1x1x01.1.wood.svg",
     "_.letter.1x1x02.1.wood.svg",
     "_.letter.1x1x03.1.wood.svg",
     "_.letter.1x1x04.1.wood.svg",
     "_.letter.1x1x05.1.wood.svg",
     "_.letter.1x1x06.1.wood.svg",
     "_.letter.1x1x07.1.wood.svg",
     "_.letter.1x1x08.1.wood.svg",
     "_.letter.1x1x09.1.wood.svg",
     "_.letter.1x1x10.1.wood.svg",
     "_.letter.1x1x11.1.wood.svg",
     "_.letter.1x1x12.1.wood.svg",
     "_.letter.1x1x13.1.wood.svg",
     "_.letter.1x1x14.1.wood.svg",
     "_.letter.1x1x15.1.wood.svg",
     "_.letter.1x1x16.1.wood.svg",
     "_.letter.1x1x17.1.wood.svg",
     "_.letter.1x1x18.1.wood.svg",
     "_.letter.1x1x19.1.wood.svg",
     "_.letter.1x1x20.1.wood.svg",
     "_.letter.1x1x21.1.wood.svg",
     "_.letter.1x1x22.1.wood.svg",
     "_.letter.1x1x23.1.wood.svg",
     "_.letter.1x1x24.1.wood.svg",
     "_.letter.1x1x25.1.wood.svg",
     "_.letter.1x1x26.1.wood.svg"
    ],
    "tx": "wood"
   },
   {
    "id": "ye4mx100",
    "lid": "sD_SB100",
    "name": "_.number",
    "type": "token",
    "bg": "1",
    "media": [
     "_.number.1x1x01.1.wood.svg",
     "_.number.1x1x02.1.wood.svg",
     "_.number.1x1x03.1.wood.svg",
     "_.number.1x1x04.1.wood.svg",
     "_.number.1x1x05.1.wood.svg",
     "_.number.1x1x06.1.wood.svg",
     "_.number.1x1x07.1.wood.svg",
     "_.number.1x1x08.1.wood.svg",
     "_.number.1x1x09.1.wood.svg",
     "_.number.1x1x10.1.wood.svg"
    ],
    "tx": "wood"
   },
   {
    "id": "FFnzp100",
    "lid": "oZX62300",
    "name": "_.plain",
    "type": "token",
    "bg": "0",
    "media": [
     "_.plain.1x1x1.0.wood.png"
    ],
    "tx": "wood"
   },
   {
    "id": "L1WtG000",
    "lid": "Hn18v200",
    "name": "_.symbol",
    "type": "token",
    "bg": "1",
    "media": [
     "_.symbol.1x1x1.1.wood.svg",
     "_.symbol.1x1x2.1.wood.svg",
     "_.symbol.1x1x3.1.wood.svg"
    ],
    "tx": "wood"
   },
   {
    "id": "u4qfn000",
    "lid": "HsCXs000",
    "name": "chess.bishop",
    "type": "token",
    "bg": "0",
    "media": [
     "chess.bishop.1x1x1.0.wood.svg",
     "chess.bishop.1x1x2.0.wood.svg"
    ],
    "tx": "wood"
   },
   {
    "id": "YWUf3200",
    "lid": "tqNbQ200",
    "name": "chess.king",
    "type": "token",
    "bg": "0",
    "media": [
     "chess.king.1x1x1.0.wood.svg",
     "chess.king.1x1x2.0.wood.svg"
    ],
    "tx": "wood"
   },
   {
    "id": "rMN_X100",
    "lid": "zKVSU200",
    "name": "chess.knight",
    "type": "token",
    "bg": "0",
    "media": [
     "chess.knight.1x1x1.0.wood.svg",
     "chess.knight.1x1x2.0.wood.svg"
    ],
    "tx": "wood"
   },
   {
    "id": "gOcNT200",
    "lid": "Z5pQC000",
    "name": "chess.pawn",
    "type": "token",
    "bg": "0",
    "media": [
     "chess.pawn.1x1x1.0.wood.svg",
     "chess.pawn.1x1x2.0.wood.svg"
    ],
    "tx": "wood"
   },
   {
    "id": "BISOH200",
    "lid": "mwxyq000",
    "name": "chess.queen",
    "type": "token",
    "bg": "0",
    "media": [
     "chess.queen.1x1x1.0.wood.svg",
     "chess.queen.1x1x2.0.wood.svg"
    ],
    "tx": "wood"
   },
   {
    "id": "GYWId200",
    "lid": "f_9xm000",
    "name": "chess.rook",
    "type": "token",
    "bg": "0",
    "media": [
     "chess.rook.1x1x1.0.wood.svg",
     "chess.rook.1x1x2.0.wood.svg"
    ],
    "tx": "wood"
   }
  ],
  "other": [
   {
    "id": "hFoyZ200",
    "lid": "lPebe300",
    "name": "_.d10Dark",
    "type": "other",
    "d": 5,
    "bg": "1",
    "media": [
     "_.d10Dark.1x1x01x5.1.svg",
     "_.d10Dark.1x1x02x5.1.svg",
     "_.d10Dark.1x1x03x5.1.svg",
     "_.d10Dark.1x1x04x5.1.svg",
     "_.d10Dark.1x1x05x5.1.svg",
     "_.d10Dark.1x1x06x5.1.svg",
     "_.d10Dark.1x1x07x5.1.svg",
     "_.d10Dark.1x1x08x5.1.svg",
     "_.d10Dark.1x1x09x5.1.svg",
     "_.d10Dark.1x1x10x5.1.svg"
    ],
    "base": "_.d10Dark.1x1x00x5.1.png",
    "mask": "_.d10Dark.1x1xXXx5.1.svg"
   },
   {
    "id": "PW2rJ000",
    "lid": "tVzk3200",
    "name": "_.d10Light",
    "type": "other",
    "d": 5,
    "bg": "2",
    "media": [
     "_.d10Light.1x1x01x5.2.svg",
     "_.d10Light.1x1x02x5.2.svg",
     "_.d10Light.1x1x03x5.2.svg",
     "_.d10Light.1x1x04x5.2.svg",
     "_.d10Light.1x1x05x5.2.svg",
     "_.d10Light.1x1x06x5.2.svg",
     "_.d10Light.1x1x07x5.2.svg",
     "_.d10Light.1x1x08x5.2.svg",
     "_.d10Light.1x1x09x5.2.svg",
     "_.d10Light.1x1x10x5.2.svg"
    ],
    "base": "_.d10Light.1x1x00x5.2.png",
    "mask": "_.d10Light.1x1xXXx5.2.svg"
   },
   {
    "id": "v8Vvg200",
    "lid": "aeS5y000",
    "name": "_.d12Dark",
    "type": "other",
    "d": 5,
    "bg": "1",
    "media": [
     "_.d12Dark.1x1x01x5.1.svg",
     "_.d12Dark.1x1x02x5.1.svg",
     "_.d12Dark.1x1x03x5.1.svg",
     "_.d12Dark.1x1x04x5.1.svg",
     "_.d12Dark.1x1x05x5.1.svg",
     "_.d12Dark.1x1x06x5.1.svg",
     "_.d12Dark.1x1x07x5.1.svg",
     "_.d12Dark.1x1x08x5.1.svg",
     "_.d12Dark.1x1x09x5.1.svg",
     "_.d12Dark.1x1x10x5.1.svg",
     "_.d12Dark.1x1x11x5.1.svg",
     "_.d12Dark.1x1x12x5.1.svg"
    ],
    "base": "_.d12Dark.1x1x00x5.1.png",
    "mask": "_.d12Dark.1x1xXXx5.1.svg"
   },
   {
    "id": "KWvBF000",
    "lid": "KKD3z300",
    "name": "_.d12Light",
    "type": "other",
    "d": 5,
    "bg": "2",
    "media": [
     "_.d12Light.1x1x01x5.2.svg",
     "_.d12Light.1x1x02x5.2.svg",
     "_.d12Light.1x1x03x5.2.svg",
     "_.d12Light.1x1x04x5.2.svg",
     "_.d12Light.1x1x05x5.2.svg",
     "_.d12Light.1x1x06x5.2.svg",
     "_.d12Light.1x1x07x5.2.svg",
     "_.d12Light.1x1x08x5.2.svg",
     "_.d12Light.1x1x09x5.2.svg",
     "_.d12Light.1x1x10x5.2.svg",
     "_.d12Light.1x1x11x5.2.svg",
     "_.d12Light.1x1x12x5.2.svg"
    ],
    "base": "_.d12Light.1x1x00x5.2.png",
    "mask": "_.d12Light.1x1xXXx5.2.svg"
   },
   {
    "id": "y6zKl100",
    "lid": "z7DUO100",
    "name": "_.d20Dark",
    "type": "other",
    "d": 5,
    "bg": "1",
    "media": [
     "_.d20Dark.1x1x01x5.1.svg",
     "_.d20Dark.1x1x02x5.1.svg",
     "_.d20Dark.1x1x03x5.1.svg",
     "_.d20Dark.1x1x04x5.1.svg",
     "_.d20Dark.1x1x05x5.1.svg",
     "_.d20Dark.1x1x06x5.1.svg",
     "_.d20Dark.1x1x07x5.1.svg",
     "_.d20Dark.1x1x08x5.1.svg",
     "_.d20Dark.1x1x09x5.1.svg",
     "_.d20Dark.1x1x10x5.1.svg",
     "_.d20Dark.1x1x11x5.1.svg",
     "_.d20Dark.1x1x12x5.1.svg",
     "_.d20Dark.1x1x13x5.1.svg",
     "_.d20Dark.1x1x14x5.1.svg",
     "_.d20Dark.1x1x15x5.1.svg",
     "_.d20Dark.1x1x16x5.1.svg",
     "_.d20Dark.1x1x17x5.1.svg",
     "_.d20Dark.1x1x18x5.1.svg",
     "_.d20Dark.1x1x19x5.1.svg",
     "_.d20Dark.1x1x20x5.1.svg"
    ],
    "base": "_.d20Dark.1x1x00x5.1.png",
    "mask": "_.d20Dark.1x1xXXx5.1.svg"
   },
   {
    "id": "Gz-zS200",
    "lid": "eIMc_300",
    "name": "_.d20Light",
    "type": "other",
    "d": 5,
    "bg": "2",
    "media": [
     "_.d20Light.1x1x01x5.2.svg",
     "_.d20Light.1x1x02x5.2.svg",
     "_.d20Light.1x1x03x5.2.svg",
     "_.d20Light.1x1x04x5.2.svg",
     "_.d20Light.1x1x05x5.2.svg",
     "_.d20Light.1x1x06x5.2.svg",
     "_.d20Light.1x1x07x5.2.svg",
     "_.d20Light.1x1x08x5.2.svg",
     "_.d20Light.1x1x09x5.2.svg",
     "_.d20Light.1x1x10x5.2.svg",
     "_.d20Light.1x1x11x5.2.svg",
     "_.d20Light.1x1x12x5.2.svg",
     "_.d20Light.1x1x13x5.2.svg",
     "_.d20Light.1x1x14x5.2.svg",
     "_.d20Light.1x1x15x5.2.svg",
     "_.d20Light.1x1x16x5.2.svg",
     "_.d20Light.1x1x17x5.2.svg",
     "_.d20Light.1x1x18x5.2.svg",
     "_.d20Light.1x1x19x5.2.svg",
     "_.d20Light.1x1x20x5.2.svg"
    ],
    "base": "_.d20Light.1x1x00x5.2.png",
    "mask": "_.d20Light.1x1xXXx5.2.svg"
   },
   {
    "id": "pJtgf000",
    "lid": "SHt9A300",
    "name": "_.d4Dark",
    "type": "other",
    "d": 5,
    "bg": "1",
    "media": [
     "_.d4Dark.1x1x1x5.1.svg",
     "_.d4Dark.1x1x2x5.1.svg",
     "_.d4Dark.1x1x3x5.1.svg",
     "_.d4Dark.1x1x4x5.1.svg"
    ],
    "base": "_.d4Dark.1x1x0x5.1.png",
    "mask": "_.d4Dark.1x1xXx5.1.svg"
   },
   {
    "id": "j8hqf000",
    "lid": "xY7Gr200",
    "name": "_.d4Light",
    "type": "other",
    "d": 5,
    "bg": "2",
    "media": [
     "_.d4Light.1x1x1x5.2.svg",
     "_.d4Light.1x1x2x5.2.svg",
     "_.d4Light.1x1x3x5.2.svg",
     "_.d4Light.1x1x4x5.2.svg"
    ],
    "base": "_.d4Light.1x1x0x5.2.png",
    "mask": "_.d4Light.1x1xXx5.2.svg"
   },
   {
    "id": "bc_Ix000",
    "lid": "jbmiY200",
    "name": "_.d6Dark",
    "type": "other",
    "d": 5,
    "bg": "1",
    "media": [
     "_.d6Dark.1x1x1x5.1.svg",
     "_.d6Dark.1x1x2x5.1.svg",
     "_.d6Dark.1x1x3x5.1.svg",
     "_.d6Dark.1x1x4x5.1.svg",
     "_.d6Dark.1x1x5x5.1.svg",
     "_.d6Dark.1x1x6x5.1.svg"
    ],
    "base": "_.d6Dark.1x1x0x5.1.png",
    "mask": "_.d6Dark.1x1xXx5.1.svg"
   },
   {
    "id": "a8cCb000",
    "lid": "u7ZAS100",
    "name": "_.d6Light",
    "type": "other",
    "d": 5,
    "bg": "2",
    "media": [
     "_.d6Light.1x1x1x5.2.svg",
     "_.d6Light.1x1x2x5.2.svg",
     "_.d6Light.1x1x3x5.2.svg",
     "_.d6Light.1x1x4x5.2.svg",
     "_.d6Light.1x1x5x5.2.svg",
     "_.d6Light.1x1x6x5.2.svg"
    ],
    "base": "_.d6Light.1x1x0x5.2.png",
    "mask": "_.d6Light.1x1xXx5.2.svg"
   },
   {
    "id": "ZyitE300",
    "lid": "xCPfK300",
    "name": "_.d8Dark",
    "type": "other",
    "d": 5,
    "bg": "1",
    "media": [
     "_.d8Dark.1x1x1x5.1.svg",
     "_.d8Dark.1x1x2x5.1.svg",
     "_.d8Dark.1x1x3x5.1.svg",
     "_.d8Dark.1x1x4x5.1.svg",
     "_.d8Dark.1x1x5x5.1.svg",
     "_.d8Dark.1x1x6x5.1.svg",
     "_.d8Dark.1x1x7x5.1.svg",
     "_.d8Dark.1x1x8x5.1.svg"
    ],
    "base": "_.d8Dark.1x1x0x5.1.png",
    "mask": "_.d8Dark.1x1xXx5.1.svg"
   },
   {
    "id": "Zavll000",
    "lid": "obzEu200",
    "name": "_.d8Light",
    "type": "other",
    "d": 5,
    "bg": "2",
    "media": [
     "_.d8Light.1x1x1x5.2.svg",
     "_.d8Light.1x1x2x5.2.svg",
     "_.d8Light.1x1x3x5.2.svg",
     "_.d8Light.1x1x4x5.2.svg",
     "_.d8Light.1x1x5x5.2.svg",
     "_.d8Light.1x1x6x5.2.svg",
     "_.d8Light.1x1x7x5.2.svg",
     "_.d8Light.1x1x8x5.2.svg"
    ],
    "base": "_.d8Light.1x1x0x5.2.png",
    "mask": "_.d8Light.1x1xXx5.2.svg"
   },
   {
    "id": "gXCJX200",
    "lid": "selr5000",
    "name": "_.dicemat",
    "type": "other",
    "w": 4,
    "bg": "#808080",
    "media": [
     "_.dicemat.4x4x1x2.jpg"
    ]
   },
   {
    "id": "rEH5X200",
    "lid": "FvPx9300",
    "name": "_.dicemat",
    "type": "other",
    "w": 8,
    "d": 5,
    "bg": "#808080",
    "media": [
     "_.dicemat.8x8x1x5.png"
    ]
   },
   {
    "id": "BQ9I2100",
    "lid": "MDuQt000",
    "name": "_.fateDark",
    "type": "other",
    "d": 5,
    "bg": "1",
    "media": [
     "_.fateDark.1x1x1x5.1.svg",
     "_.fateDark.1x1x2x5.1.svg",
     "_.fateDark.1x1x3x5.1.svg",
     "_.fateDark.1x1x4x5.1.svg",
     "_.fateDark.1x1x5x5.1.svg",
     "_.fateDark.1x1x6x5.1.svg"
    ],
    "base": "_.fateDark.1x1x0x5.1.png",
    "mask": "_.fateDark.1x1xXx5.1.svg"
   },
   {
    "id": "iCBYt200",
    "lid": "MTvWD100",
    "name": "_.fateLight",
    "type": "other",
    "d": 5,
    "bg": "2",
    "media": [
     "_.fateLight.1x1x1x5.2.svg",
     "_.fateLight.1x1x2x5.2.svg",
     "_.fateLight.1x1x3x5.2.svg",
     "_.fateLight.1x1x4x5.2.svg",
     "_.fateLight.1x1x5x5.2.svg",
     "_.fateLight.1x1x6x5.2.svg"
    ],
    "base": "_.fateLight.1x1x0x5.2.png",
    "mask": "_.fateLight.1x1xXx5.2.svg"
   }
  ],
  "badge": [
   {
    "id": "ED1At200",
    "lid": "Jxa0k200",
    "name": "_.badge",
    "type": "badge",
    "bg": "#808080",
    "media": [
     "_.badge.svg"
    ]
   },
   {
    "id": "HP4Ig300",
    "lid": "RvGjJ000",
    "name": "_.target",
    "type": "badge",
    "bg": "#808080",
    "media": [
     "_.target.svg"
    ]
   },
   {
    "id": "B5K2G200",
    "lid": "wRe_l200",
    "name": "drop",
    "type": "badge",
    "bg": "#808080",
    "media": [
     "drop.svg"
    ]
   },
   {
    "id": "zKY2a100",
    "lid": "wgQLZ100",
    "name": "mark",
    "type": "badge",
    "bg": "#808080",
    "media": [
     "mark.svg"
    ]
   },
   {
    "id": "KVbW6300",
    "lid": "Wvh__000",
    "name": "shield",
    "type": "badge",
    "bg": "#808080",
    "media": [
     "shield.svg"
    ]
   }
  ],
  "material": [
   {
    "id": "brTTG000",
    "lid": "CIZcg300",
    "name": "linen",
    "type": "material",
    "bg": "#808080",
    "media": [
     "linen.png"
    ]
   },
   {
    "id": "QjDAr300",
    "lid": "MOevM100",
    "name": "none",
    "type": "material",
    "bg": "#808080",
    "media": [
     "none.png"
    ]
   },
   {
    "id": "H4W0w000",
    "lid": "Hb9tz200",
    "name": "paper",
    "type": "material",
    "bg": "#808080",
    "media": [
     "paper.png"
    ]
   },
   {
    "id": "YDTSJ000",
    "lid": "LDpOJ000",
    "name": "rough",
    "type": "material",
    "bg": "#808080",
    "media": [
     "rough.png"
    ]
   },
   {
    "id": "ljAne100",
    "lid": "wS-60300",
    "name": "wood",
    "type": "material",
    "bg": "#808080",
    "media": [
     "wood.png"
    ]
   }
  ]
 },
 "credits": "The **Classic** snapshot is part of FreeBeeGee and released under the terms of the AGPL-3.0. It contains assets by:\n\n* Marble Texture CC BY-SA 3.0 by SimoonMurray\n* Go boards AGPL-3.0 by [svenja](https://github.com/svenja/)\n* Pieces by [game-icons.net](https://game-icons.net/) / CC BY 3.0, renamed and slightly modified:\n  * Chess pieces by Skoll\n  * Griffin shield icon by Delapouite\n* Status icons by [game-icons.net](https://game-icons.net/) / CC BY 3.0, renamed and slightly modified:\n  * broken-heart, bubbling-bowl, explosion-rays, magnet, manacles, power-lightning, psychic-waves, resonance, spider-web, stone-block, water-splash by Lorc\n  * griffin-shield, target-poster by Delapouite\n  * water-drop by sbed\n",
 "width": 4096,
 "height": 4096
}